superagent/__init__.py
superagent/client.py
superagent/core/__init__.py
superagent/core/api_error.py
superagent/core/client_wrapper.py
superagent/core/datetime_utils.py
superagent/core/file.py
superagent/core/http_client.py
superagent/core/jsonable_encoder.py
superagent/core/pydantic_utilities.py
superagent/core/query_encoder.py
superagent/core/remove_none_from_dict.py
superagent/core/request_options.py
superagent/environment.py
superagent/errors/__init__.py
superagent/errors/unprocessable_entity_error.py
superagent/py.typed
superagent/resources/__init__.py
superagent/resources/agent/__init__.py
superagent/resources/agent/client.py
superagent/resources/api_key/__init__.py
superagent/resources/api_key/client.py
superagent/resources/api_user/__init__.py
superagent/resources/api_user/client.py
superagent/resources/datasource/__init__.py
superagent/resources/datasource/client.py
superagent/resources/llm/__init__.py
superagent/resources/llm/client.py
superagent/resources/tool/__init__.py
superagent/resources/tool/client.py
superagent/resources/vector_database/__init__.py
superagent/resources/vector_database/client.py
superagent/resources/workflow/__init__.py
superagent/resources/workflow/client.py
superagent/resources/workflow_config/__init__.py
superagent/resources/workflow_config/client.py
superagent/types/__init__.py
superagent/types/agent_datasosurce_list.py
superagent/types/agent_list.py
superagent/types/agent_tool_list.py
superagent/types/agent_type.py
superagent/types/api_key_create.py
superagent/types/api_key_create_model.py
superagent/types/api_key_list.py
superagent/types/app_models_request_api_key.py
superagent/types/app_models_request_api_user.py
superagent/types/app_models_request_datasource.py
superagent/types/app_models_request_llm.py
superagent/types/app_models_request_vector_db.py
superagent/types/app_models_request_workflow.py
superagent/types/app_models_request_workflow_step.py
superagent/types/app_models_response_agent.py
superagent_py-0.2.40.dist-info/LICENSE
superagent_py-0.2.40.dist-info/METADATA
superagent_py-0.2.40.dist-info/WHEEL
superagent_py-0.2.40.dist-info/RECORD
